pandas_eda_check/__init__.py
pandas_eda_check-0.1.1.dist-info/LICENSE
pandas_eda_check-0.1.1.dist-info/METADATA
pandas_eda_check-0.1.1.dist-info/WHEEL
pandas_eda_check-0.1.1.dist-info/top_level.txt
pandas_eda_check-0.1.1.dist-info/RECORD
