Metadata-Version: 2.1
Name: pandas-eda-check
Version: 0.1.1
Summary: Quick EDA utility to summarize unique and missing values in pandas DataFrames.
Home-page: https://github.com/CS-Ponkoj/pandas_eda_check
Author: Ponkoj Shill
Author-email: csponkoj@gmail.com
License: MIT
Classifier: Programming Language :: Python :: 3
Classifier: Intended Audience :: Science/Research
Classifier: Topic :: Scientific/Engineering :: Information Analysis
Classifier: License :: OSI Approved :: MIT License
Classifier: Operating System :: OS Independent
Requires-Python: >=3.6
License-File: LICENSE
Requires-Dist: pandas
